README.txt
setup.py
inquant/__init__.py
inquant.contentmirror.plone.egg-info/PKG-INFO
inquant.contentmirror.plone.egg-info/SOURCES.txt
inquant.contentmirror.plone.egg-info/dependency_links.txt
inquant.contentmirror.plone.egg-info/entry_points.txt
inquant.contentmirror.plone.egg-info/namespace_packages.txt
inquant.contentmirror.plone.egg-info/not-zip-safe
inquant.contentmirror.plone.egg-info/requires.txt
inquant.contentmirror.plone.egg-info/top_level.txt
inquant/contentmirror/__init__.py
inquant/contentmirror/plone/README.rst
inquant/contentmirror/plone/__init__.py
inquant/contentmirror/plone/configure.zcml
inquant/contentmirror/plone/utils.py
inquant/contentmirror/plone/browser/__init__.py
inquant/contentmirror/plone/browser/configure.zcml
inquant/contentmirror/plone/browser/mirror-info.pt
inquant/contentmirror/plone/browser/viewlets.py
inquant/contentmirror/plone/browser/views.py
inquant/contentmirror/plone/profiles/default/actions.xml