Metadata-Version: 1.0
Name: inquant.contentmirror.plone
Version: 0.2
Summary: Plone UI for contentmirror
Home-page: UNKNOWN
Author: Stefan Eletzhofer
Author-email: stefan.eletzhofer@inquant.de
License: GPL
Platform: UNKNOWN
Classifier: Framework :: Plone
Classifier: Framework :: Zope2
Classifier: Framework :: Zope3
Classifier: Programming Language :: Python
Classifier: Topic :: Software Development :: Libraries :: Python Modules
